<?xml version="1.0" encoding="UTF-8"?>
<!DOCTYPE mapper PUBLIC "-//mybatis.org//DTD Mapper 3.0//EN"
        "http://mybatis.org/dtd/mybatis-3-mapper.dtd">
<mapper namespace="com.yachaerang.batch.repository.DailyPriceRepository">
    <resultMap id="dailyPriceResultMap"
               type="com.yachaerang.batch.domain.entity.DailyPrice">
        <id property="dailyPriceId" column="daily_price_id"/>
        <result property="productCode" column="product_code"/>
        <result property="priceDate" column="price_date"/>
        <result property="price" column="price"/>
        <result property="priceChange" column="price_change"/>
        <result property="priceChangeRate" column="price_change_rate"/>
    </resultMap>

    <!-- 특정 상품의 가장 최근 가격 조회(특정 날짜 이전) -->
    <select id="findLatestPriceByProductCode"
            resultType="java.lang.Long">
        SELECT price
        FROM daily_price
        WHERE product_code = #{productCode}
          AND price_date &lt; #{priceDate}
        ORDER BY price_date DESC
            LIMIT 1
    </select>

    <!-- List Save -->
    <insert id="saveAll" parameterType="list">
        INSERT INTO daily_price
        (product_code, price_date, price, price_change, price_change_rate)
        VALUES
        <foreach collection="list" item="item" separator=",">
            (#{item.productCode}, #{item.priceDate}, #{item.price}, #{item.priceChange}, #{item.priceChangeRate})
        </foreach>
    </insert>

    <!-- product + priceDate 존재 여부 체크 (Boolean) -->
    <select id="existsByProductAndPriceDate"
            parameterType="map" resultType="boolean">
        SELECT EXISTS (
            SELECT 1
            FROM daily_price
            WHERE product_code = #{product.productCode}
              AND price_date = #{priceDate}
        )
    </select>

    <!-- 특정 상품의 특정 날짜 가격 조회 -->
    <select id="findPriceByProductCodeAndDate" resultType="java.lang.Long">
        SELECT price
        FROM daily_price
        WHERE product_code = #{productCode}
          AND price_date = #{priceDate}
            LIMIT 1
    </select>

    <!-- 특정 상품의 주차 내 가장 빠른 날짜의 가격 조회 -->
    <select id="findEarliestPriceInWeek" resultType="java.lang.Long">
        SELECT price
        FROM daily_price
        WHERE product_code = #{productCode}
          AND price_date BETWEEN #{weekStartDate} AND #{weekEndDate}
        ORDER BY price_date ASC
            LIMIT 1
    </select>

    <!-- 특정 상품의 주차 내 가장 마지막 날짜의 가격 조회 -->
    <select id="findLatestPriceInWeek" resultType="java.lang.Long">
        SELECT price
        FROM daily_price
        WHERE product_code = #{productCode}
          AND price_date BETWEEN #{weekStartDate} AND #{weekEndDate}
        ORDER BY price_date DESC
            LIMIT 1
    </select>

    <!-- 특정 상품의 월 내 가장 빠른 날짜의 가격 조회 -->
    <select id="findEarliestPriceInMonth" resultType="java.lang.Long">
        SELECT price
        FROM daily_price
        WHERE product_code = #{productCode}
          AND price_date BETWEEN #{monthStartDate} AND #{monthEndDate}
        ORDER BY price_date ASC
            LIMIT 1
    </select>

    <!-- 특정 상품의 월 내 가장 마지막 날짜의 가격 조회 -->
    <select id="findLatestPriceInMonth" resultType="java.lang.Long">
        SELECT price
        FROM daily_price
        WHERE product_code = #{productCode}
          AND price_date BETWEEN #{monthStartDate} AND #{monthEndDate}
        ORDER BY price_date DESC
            LIMIT 1
    </select>
</mapper>